kimi4free/__init__.py
kimi4free/client.py
kimi4free-0.1.3.dist-info/METADATA
kimi4free-0.1.3.dist-info/WHEEL
kimi4free-0.1.3.dist-info/top_level.txt
kimi4free-0.1.3.dist-info/RECORD
