Metadata-Version: 2.1
Name: kimi4free
Version: 0.1.3
Summary: A way of using Kimi for free; even with login features.
Home-page: https://github.com/SertraFurr/kimi4free
Author: SertraFurr
Classifier: Programming Language :: Python :: 3
Classifier: License :: OSI Approved :: MIT License
Classifier: Operating System :: OS Independent
Requires-Python: >=3.7
Requires-Dist: requests
